Workbook

Sheet Parametros
A1: Concepto | B1: Valor | C1: Descripcion
A2: Tarifa PO (COP/hora) | B2: 90000 | C2: Tarifa hora Product Owner
A3: Tarifa SM (COP/hora) | B3: 80000 | C3: Tarifa hora Scrum Master
A4: Tarifa Dev (COP/hora) | B4: 65000 | C4: Tarifa hora Desarrollador
A5: Tarifa QA (COP/hora) | B5: 55000 | C5: Tarifa hora QA / Tester
A6: Horas por sprint (por persona) | B6: 80 | C6: Horas por persona por sprint
A7: Numero de sprints | B7: 3 | C7: Cantidad planificada de sprints
A8: Gastos Administrativos (%) | B8: 0.15 | C8: Costos indirectos (administracion, gestion, etc.)
A9: Imprevistos (%) | B9: 0.1 | C9: Colchon de riesgo sobre el costo total

Sheet Equipo_Sprints
A1: Sprint | B1: Rol | C1: Nombre | D1: Tarifa (COP/hora) | E1: Horas planificadas | F1: Costo planificado (COP) | G1: Horas reales | H1: Costo real (COP) | I1: Var % costo
A2: Sprint 1 | B2: Product Owner | C2: David Eduardo Flórez Durán | D2: =Parametros!B2 -> 90000 | E2: 90 | F2: =D2*E2 -> 8100000 | G2: 60 | H2: =D2*G2 -> 5400000 | I2: =IF(F2>0,(H2/F2)-1,0) -> -0.33333333
A3: Sprint 1 | B3: Scrum Master | C3: Juan David Ordoñez Ferrerira | D3: =Parametros!B3 -> 80000 | E3: 70 | F3: =D3*E3 -> 5600000 | G3: 50 | H3: =D3*G3 -> 4000000 | I3: =IF(F3>0,(H3/F3)-1,0) -> -0.28571429
A4: Sprint 1 | B4: Developer | C4: David Ricardo Carvajal Barragán | D4: =Parametros!B4 -> 65000 | E4: 60 | F4: =D4*E4 -> 3900000 | G4: 55 | H4: =D4*G4 -> 3575000 | I4: =IF(F4>0,(H4/F4)-1,0) -> -0.083333333
A5: Sprint 1 | B5: Developer | C5: Juan Pablo Arenas Avendaño | D5: =Parametros!B4 -> 65000 | E5: 35 | F5: =D5*E5 -> 2275000 | G5: 25 | H5: =D5*G5 -> 1625000 | I5: =IF(F5>0,(H5/F5)-1,0) -> -0.28571429
A6: Sprint 1 | B6: Developer | C6: José David Mora Patiño | D6: =Parametros!B4 -> 65000 | E6: 50 | F6: =D6*E6 -> 3250000 | G6: 40 | H6: =D6*G6 -> 2600000 | I6: =IF(F6>0,(H6/F6)-1,0) -> -0.2
A7: Sprint 1 | B7: QA | C7: Gabriel Arturo Sastoque Cadena | D7: =Parametros!B5 -> 55000 | E7: 15 | F7: =D7*E7 -> 825000 | G7: 10 | H7: =D7*G7 -> 550000 | I7: =IF(F7>0,(H7/F7)-1,0) -> -0.33333333
A8: Sprint 1 | B8: Developer | C8: Santiago Cifuentes Cardenas | D8: =Parametros!B4 -> 65000 | E8: 25 | F8: =D8*E8 -> 1625000 | G8: 15 | H8: =D8*G8 -> 975000 | I8: =IF(F8>0,(H8/F8)-1,0) -> -0.4
A9: Sprint 1 | B9: Developer | C9: Gabriel Matías Rodriguez Castro | D9: =Parametros!B4 -> 65000 | E9: 25 | F9: =D9*E9 -> 1625000 | G9: 15 | H9: =D9*G9 -> 975000 | I9: =IF(F9>0,(H9/F9)-1,0) -> -0.4
A10: Sprint 1 | B10: Developer | C10: Simón Perez Gómez | D10: =Parametros!B4 -> 65000 | E10: 25 | F10: =D10*E10 -> 1625000 | G10: 15 | H10: =D10*G10 -> 975000 | I10: =IF(F10>0,(H10/F10)-1,0) -> -0.4
A11: TOTAL Sprint 1 | F11: =SUM(F2:F10) -> 28825000 | H11: =SUM(H2:H10) -> 20675000 | I11: =IF(F11>0,(H11/F11)-1,0) -> -0.28274068
A13: Sprint 2 | B13: Product Owner | C13: David Eduardo Flórez Durán | D13: =Parametros!B2 -> 90000 | E13: 70 | F13: =D13*E13 -> 6300000 | G13: 65 | H13: =D13*G13 -> 5850000 | I13: =IF(F13>0,(H13/F13)-1,0) -> -0.071428571
A14: Sprint 2 | B14: Scrum Master | C14: Juan David Ordoñez Ferrerira | D14: =Parametros!B3 -> 80000 | E14: 80 | F14: =D14*E14 -> 6400000 | G14: 70 | H14: =D14*G14 -> 5600000 | I14: =IF(F14>0,(H14/F14)-1,0) -> -0.125
A15: Sprint 2 | B15: Developer | C15: David Ricardo Carvajal Barragán | D15: =Parametros!B4 -> 65000 | E15: 70 | F15: =D15*E15 -> 4550000 | G15: 55 | H15: =D15*G15 -> 3575000 | I15: =IF(F15>0,(H15/F15)-1,0) -> -0.21428571
A16: Sprint 2 | B16: Developer | C16: Juan Pablo Arenas Avendaño | D16: =Parametros!B4 -> 65000 | E16: 50 | F16: =D16*E16 -> 3250000 | G16: 45 | H16: =D16*G16 -> 2925000 | I16: =IF(F16>0,(H16/F16)-1,0) -> -0.1
A17: Sprint 2 | B17: Developer | C17: José David Mora Patiño | D17: =Parametros!B4 -> 65000 | E17: 65 | F17: =D17*E17 -> 4225000 | G17: 60 | H17: =D17*G17 -> 3900000 | I17: =IF(F17>0,(H17/F17)-1,0) -> -0.076923077
A18: Sprint 2 | B18: Developer | C18: Santiago Cifuentes Cardenas | D18: =Parametros!B4 -> 65000 | E18: 40 | F18: =D18*E18 -> 2600000 | G18: 30 | H18: =D18*G18 -> 1950000 | I18: =IF(F18>0,(H18/F18)-1,0) -> -0.25
A19: Sprint 2 | B19: Developer | C19: Simón Perez Gómez | D19: =Parametros!B4 -> 65000 | E19: 50 | F19: =D19*E19 -> 3250000 | G19: 45 | H19: =D19*G19 -> 2925000 | I19: =IF(F19>0,(H19/F19)-1,0) -> -0.1
A20: Sprint 2 | B20: Developer | C20: Gabriel Matías Rodriguez Castro | D20: =Parametros!B4 -> 65000 | E20: 65 | F20: =D20*E20 -> 4225000 | G20: 50 | H20: =D20*G20 -> 3250000 | I20: =IF(F20>0,(H20/F20)-1,0) -> -0.23076923
A21: Sprint 2 | B21: QA | C21: Gabriel Arturo Sastoque Cadena | D21: =Parametros!B5 -> 55000 | E21: 50 | F21: =D21*E21 -> 2750000 | G21: 50 | H21: =D21*G21 -> 2750000 | I21: =IF(F21>0,(H21/F21)-1,0) -> 0
A22: TOTAL Sprint 2 | F22: =SUM(F13:F21) -> 37550000 | H22: =SUM(H13:H21) -> 32725000 | I22: =IF(F22>0,(H22/F22)-1,0) -> -0.12849534
A24: Sprint 3 | B24: Product Owner | C24: David Eduardo Flórez Durán | D24: =Parametros!B2 -> 90000 | E24: 70 | F24: =D24*E24 -> 6300000 | G24: 60 | H24: =D24*G24 -> 5400000 | I24: =IF(F24>0,(H24/F24)-1,0) -> -0.14285714
A25: Sprint 3 | B25: Scrum Master | C25: Juan David Ordoñez Ferrerira | D25: =Parametros!B3 -> 80000 | E25: 60 | F25: =D25*E25 -> 4800000 | G25: 55 | H25: =D25*G25 -> 4400000 | I25: =IF(F25>0,(H25/F25)-1,0) -> -0.083333333
A26: Sprint 3 | B26: Developer | C26: David Ricardo Carvajal Barragán | D26: =Parametros!B4 -> 65000 | E26: 55 | F26: =D26*E26 -> 3575000 | G26: 45 | H26: =D26*G26 -> 2925000 | I26: =IF(F26>0,(H26/F26)-1,0) -> -0.18181818
A27: Sprint 3 | B27: Developer | C27: Juan Pablo Arenas Avendaño | D27: =Parametros!B4 -> 65000 | E27: 50 | F27: =D27*E27 -> 3250000 | G27: 40 | H27: =D27*G27 -> 2600000 | I27: =IF(F27>0,(H27/F27)-1,0) -> -0.2
A28: Sprint 3 | B28: Developer | C28: José David Mora Patiño | D28: =Parametros!B4 -> 65000 | E28: 50 | F28: =D28*E28 -> 3250000 | G28: 40 | H28: =D28*G28 -> 2600000 | I28: =IF(F28>0,(H28/F28)-1,0) -> -0.2
A29: Sprint 3 | B29: Developer | C29: Simón Perez Gómez | D29: =Parametros!B4 -> 65000 | E29: 40 | F29: =D29*E29 -> 2600000 | G29: 40 | H29: =D29*G29 -> 2600000 | I29: =IF(F29>0,(H29/F29)-1,0) -> 0
A30: Sprint 3 | B30: Developer | C30: Santiago Cifuentes Cardenas | D30: =Parametros!B4 -> 65000 | E30: 35 | F30: =D30*E30 -> 2275000 | G30: 25 | H30: =D30*G30 -> 1625000 | I30: =IF(F30>0,(H30/F30)-1,0) -> -0.28571429
A31: Sprint 3 | B31: Developer | C31: Gabriel Matías Rodriguez Castro | D31: =Parametros!B4 -> 65000 | E31: 35 | F31: =D31*E31 -> 2275000 | G31: 35 | H31: =D31*G31 -> 2275000 | I31: =IF(F31>0,(H31/F31)-1,0) -> 0
A32: Sprint 3 | B32: QA | C32: Gabriel Arturo Sastoque Cadena | D32: =Parametros!B5 -> 55000 | E32: 80 | F32: =D32*E32 -> 4400000 | G32: 70 | H32: =D32*G32 -> 3850000 | I32: =IF(F32>0,(H32/F32)-1,0) -> -0.125
A33: TOTAL Sprint 3 | F33: =SUM(F24:F32) -> 32725000 | H33: =SUM(H24:H32) -> 28275000 | I33: =IF(F33>0,(H33/F33)-1,0) -> -0.13598167
A41: GRAN TOTAL PROYECTO | F41: =F11+F22+F33 -> 99100000 | H41: =H11+H22+H33 -> 81675000 | I41: =IF(F41>0,(H41/F41)-1,0) -> -0.17583249

Sheet Costos_Fijos
A1: Categoria | B1: Descripcion | C1: Costo mensual (COP) | D1: Meses | E1: Costo total (COP)
A2: Infraestructura/Cloud | B2: Droplet DO 2GiB/1vCPU/50GiB (servidor, VM nube) | C2: 45000 | D2: 3 | E2: =C2*D2 -> 135000
A3: Infraestructura/Cloud | B3: DO Managed MySQL (base de datos administrada) | C3: 56000 | D3: 3 | E3: =C3*D3 -> 168000
A4: Infraestructura/Cloud | B4: DO Spaces (Object Storage - almacenamiento de archivos) | C4: 18500 | D4: 3 | E4: =C4*D4 -> 55500
A5: Infraestructura/Cloud | B5: Backups Droplet (~30% del servidor) | C5: 14000 | D5: 3 | E5: =C5*D5 -> 42000
A6: Infraestructura/Cloud | B6: Dominio .com (anual) | C6: 30000 | D6: 1 | E6: =C6*D6 -> 30000
A7: Infraestructura/Cloud | B7: SSL (Let’s Encrypt - anual) | C7: 24000 | D7: 1 | E7: =C7*D7 -> 24000
A8: Operación/Oficina | B8: Coworking (9 puestos x 227.000 COP) | C8: 2043000 | D8: 3 | E8: =C8*D8 -> 6129000
A9: Operación/Oficina | B9: Papelería / impresiones | C9: 50000 | D9: 3 | E9: =C9*D9 -> 150000
A10: Hardware | B10: Alquiler portátiles i5 (9 equipos × 80.000 + IVA) | C10: 850000 | D10: 3 | E10: =C10*D10 -> 2550000
A11: Infraestructura/Red | B11: UDM-Pro (gateway/firewall) | C11: 1400000 | D11: 1 | E11: =C11*D11 -> 1400000
A12: Infraestructura/Red | B12: Switch 24 PoE (USW-24-POE) | C12: 680000 | D12: 1 | E12: =C12*D12 -> 680000
A13: Infraestructura/Red | B13: 2× AP U6 Lite | C13: 730000 | D13: 1 | E13: =C13*D13 -> 730000
... A24: Herramientas | B24: StarUML V7 Professional (3 licencias) | C24: 735000 | D24: 3 | E24: =C24*D24 -> 2205000
A25: TOTAL COSTOS FIJOS | E25: =SUM(E2:E24) -> 23046500

Sheet Resumen_Ejecutivo
A1: 📊 RESUMEN EJECUTIVO – PRESUPUESTO PROYECTO SCRUM (3 SPRINTS)
A2: Concepto | B2: Referencia / Formula | C2: Valor (COP) | D2: Notas
A3: Costo total planificado (equipo) | B3: Equipo_Sprints F26 | C3: =Equipo_Sprints!F41 -> 99100000 | D3: Suma de todos los sprints planificados
A4: Costo total real (equipo) | B4: Equipo_Sprints H26 | C4: =Equipo_Sprints!H41 -> 81675000 | D4: Suma de horas reales ejecutadas
A5: Costos fijos (infraestructura y herramientas) | B5: Costos_Fijos E8 | C5: =Costos_Fijos!E25 -> 23046500 | D5: Servidores, licencias, comunicacion
A6: Subtotal (equipo + costos fijos) | B6: C3+C5 | C6: =C3+C5 -> 122146500 | D6: Base para calcular overhead e imprevistos
A7: Gastos Administrativos (15%) | B7: Subtotal * Parametros!B8 | C7: =C6*Parametros!B8 -> 18321975 | D7: Costos indirectos de administracion
A8: Imprevistos / Contingencia (10%) | B8: Subtotal * Parametros!B9 | C8: =C6*Parametros!B9 -> 12214650 | D8: Colchon de riesgo del proyecto
A9: PRESUPUESTO TOTAL DEL PROYECTO | B9: Subtotal + Adm + Imprevistos | C9: =C6+C7+C8 -> 152683125 | D9: ✅ Valor a presentar al patrocinador
A10: Variacion global (plan vs real) | B10: (Costo real - Costo plan) / Costo plan | C10: =IF(C3>0,(C4/C3)-1,0) -> -0.17583249 | D10: Positivo = sobrecosto | Negativo = ahorro
